{"dist_classes_grouploader.md":"0d45e477","dist_classes_audioloader.md":"facfc572","dist_classes_basetexture.md":"fe331bae","dist_classes_button.md":"7370f530","dist_classes_audio.md":"ad8fb7ea","dist_classes_component.md":"fc3ace23","dist_classes_container.md":"00011682","dist_classes_rect.md":"8a88514b","dist_classes_displayobjects.md":"71bfaa9b","dist_readme.md":"3f1c27b3","dist_classes_animation.md":"8b5747e8","dist_classes_application.md":"1c3e3d24","dist_classes_imageloader.md":"b96e43b3","dist_classes_jsonloader.md":"07e7c984","dist_classes_ninepanel.md":"92baee8d","dist_classes_mask.md":"d84afaff","dist_classes_matrix.md":"7b2576fc","dist_classes_eventsystem.md":"70594633","dist_classes_graphics.md":"475b0211","dist_classes_layout.md":"22e39b2e","dist_classes_node.md":"01c2f5fe","dist_classes_renderer.md":"836bf1b4","dist_classes_resource.md":"cb044582","dist_classes_ticker.md":"a8cd2504","dist_classes_vector2.md":"1f520d95","dist_enums_textalgin.md":"a0caa2bd","dist_interfaces_icontainer.md":"53bb1482","dist_interfaces_iloader.md":"f72c7c0d","dist_interfaces_ires.md":"b9e78590","index.md":"8056059a","dist_classes_texture.md":"72ba563d","dist_classes_spritesheet.md":"1b1acc5f","dist_classes_sprite.md":"538d1d95","dist_classes_thing.md":"46c2279f","dist_modules.md":"a8f5f8f2","dist_interfaces_icomponent.md":"2ddc910a","dist_enums_touchevent.md":"48e4890d","dist_classes_spritesheetanimation.md":"3ba6a19c","dist_classes_text.md":"bc313a89","dist_classes_transform.md":"59989f8a"}
