{"dist_readme.md":"ec8c7ba0","dist_classes_application.md":"19e12bc1","dist_classes_audio.md":"f02ffaf5","dist_classes_audioloader.md":"7a24e63b","dist_classes_basecontainer.md":"2e5e587d","dist_classes_basetexture.md":"dd84b6e5","dist_classes_button.md":"00978515","dist_classes_ecs.system.md":"b2393843","dist_classes_ecs.entiy.md":"fd1f1e3d","dist_classes_ecs.component.md":"e052074d","dist_classes_container.md":"0ba2a5ef","dist_classes_ecs.word.md":"7b01d20f","dist_classes_component.md":"de7bab38","dist_classes_eventsystem.md":"3229ac0f","dist_classes_imagetexture.md":"ce5edfc9","dist_classes_jsonloader.md":"ce5d454c","dist_classes_layout.md":"0b099408","dist_classes_matrix.md":"b8c8d123","dist_classes_renderer.md":"2ca274f8","dist_classes_resource.md":"b9c0ddf0","dist_classes_sprite.md":"47b1bf12","dist_classes_texttexture.md":"891ef657","dist_enums_textalgin.md":"9a29692b","dist_classes_imageloader.md":"54aa231a","dist_classes_transform.md":"f17c381d","dist_classes_grouploader.md":"8de4c632","dist_interfaces_icontainer.md":"c340f090","dist_modules.md":"2a50cc81","dist_interfaces_icomponent.md":"4add1cc9","dist_classes_text.md":"08741b71","dist_interfaces_iloader.md":"a263cf07","dist_classes_ticker.md":"f0a1add7","index.md":"3a9ca902","dist_enums_touchevent.md":"dc977dc9","dist_modules_ecs.md":"371ca6a8","dist_classes_vector2.md":"82d9b17c"}
